odoo/addons/report_qweb_parameter/README.rst
odoo/addons/report_qweb_parameter/__init__.py
odoo/addons/report_qweb_parameter/__manifest__.py
odoo/addons/report_qweb_parameter/demo/test_report_field_length.xml
odoo/addons/report_qweb_parameter/i18n/fr.po
odoo/addons/report_qweb_parameter/i18n/pt.po
odoo/addons/report_qweb_parameter/i18n/report_qweb_parameter.pot
odoo/addons/report_qweb_parameter/models/__init__.py
odoo/addons/report_qweb_parameter/models/ir_qweb.py
odoo/addons/report_qweb_parameter/static/description/icon.png
odoo/addons/report_qweb_parameter/tests/__init__.py
odoo/addons/report_qweb_parameter/tests/test_report_qweb_parameter.py
odoo12_addon_report_qweb_parameter-12.0.1.0.2.dist-info/METADATA
odoo12_addon_report_qweb_parameter-12.0.1.0.2.dist-info/WHEEL
odoo12_addon_report_qweb_parameter-12.0.1.0.2.dist-info/top_level.txt
odoo12_addon_report_qweb_parameter-12.0.1.0.2.dist-info/RECORD
