Metadata-Version: 2.1
Name: odoo12-addon-report-qweb-parameter
Version: 12.0.1.0.2
Summary: Add new parameters for qweb templates in order to reduce field length and check minimal length
Home-page: https://github.com/OCA/reporting-engine
Author: Creu Blanca,Odoo Community Association (OCA)
Author-email: support@odoo-community.org
License: AGPL-3
Platform: UNKNOWN
Classifier: Programming Language :: Python
Classifier: Framework :: Odoo
Classifier: Framework :: Odoo :: 12.0
Classifier: License :: OSI Approved :: GNU Affero General Public License v3
Requires-Python: >=3.5
Requires-Dist: odoo (<12.1dev,>=12.0a)
